omero_rois/__init__.py
omero_rois/library.py
omero_rois-0.3.0.dist-info/LICENSE.txt
omero_rois-0.3.0.dist-info/METADATA
omero_rois-0.3.0.dist-info/WHEEL
omero_rois-0.3.0.dist-info/top_level.txt
omero_rois-0.3.0.dist-info/zip-safe
omero_rois-0.3.0.dist-info/RECORD
