Metadata-Version: 2.1
Name: omero-rois
Version: 0.3.0
Summary: OMERO Python utilities for handling regions of interest.
Home-page: https://github.com/ome/omero-rois/
Author: The Open Microscopy Team
Author-email: ome-devel@lists.openmicroscopy.org.uk
License: GPL-2.0+
Download-URL: https://github.com/ome/omero-rois//v0.3.0.tar.gz
Keywords: OMERO.CLI,plugin
Platform: UNKNOWN
Classifier: Development Status :: 4 - Beta
Classifier: Environment :: Plugins
Classifier: Intended Audience :: Developers
Classifier: Intended Audience :: End Users/Desktop
Classifier: License :: OSI Approved :: GNU General Public License v2 or later (GPLv2+)
Classifier: Natural Language :: English
Classifier: Operating System :: OS Independent
Classifier: Programming Language :: Python :: 3
Classifier: Topic :: Software Development :: Libraries :: Python Modules
Requires-Python: >=3
Requires-Dist: omero-py (>=5.6.0)
